pyvisual/__init__.py
pyvisual/assets/buttons/blue_round/clicked.png
pyvisual/assets/buttons/blue_round/hover.png
pyvisual/assets/buttons/blue_round/idle.png
pyvisual/assets/buttons/default/clicked.png
pyvisual/assets/buttons/default/hover.png
pyvisual/assets/buttons/default/idle.png
pyvisual/assets/buttons/svg/24.svg
pyvisual/assets/buttons/svg/25.svg
pyvisual/assets/buttons/svg/26.svg
pyvisual/assets/checkboxes/default/tick.png
pyvisual/assets/checkboxes/sample/checked.png
pyvisual/assets/checkboxes/sample/unchecked.png
pyvisual/assets/dropdownmenus/default/arrow.png
pyvisual/assets/fonts/anton/Anton-Regular.ttf
pyvisual/assets/fonts/roboto/Roboto-Bold.ttf
pyvisual/assets/fonts/roboto/Roboto-Regular.ttf
pyvisual/assets/gifs/loading.gif
pyvisual/assets/icons/Like/like.svg
pyvisual/assets/icons/chatbot/chatbot.png
pyvisual/assets/icons/more/arrow_right.svg
pyvisual/assets/icons/more/email.svg
pyvisual/assets/icons/more/lock.svg
pyvisual/assets/icons/more/play.svg
pyvisual/assets/icons/more/shopping.svg
pyvisual/assets/icons/window/window.ico
pyvisual/assets/icons/window/window.png
pyvisual/assets/progressbars/circular/track.png
pyvisual/assets/progressbars/circular/track_fill.png
pyvisual/assets/progressbars/default/fill.png
pyvisual/assets/progressbars/default/knob.png
pyvisual/assets/progressbars/default/track.png
pyvisual/assets/radiobuttons/sample/checked.png
pyvisual/assets/radiobuttons/sample/unchecked.png
pyvisual/assets/sliders/sample/fill.png
pyvisual/assets/sliders/sample/knob.png
pyvisual/assets/sliders/sample/track.png
pyvisual/assets/textinputs/default/active.png
pyvisual/assets/textinputs/default/idle.png
pyvisual/assets/toggles/default/off.png
pyvisual/assets/toggles/default/on.png
pyvisual/core/__init__.py
pyvisual/core/pv_app.py
pyvisual/core/pv_pages.py
pyvisual/core/pv_sidebar.py
pyvisual/core/pv_window.py
pyvisual/ui/__init__.py
pyvisual/ui/__pycache__/__init__.cpython-310.pyc
pyvisual/ui/experimental/__init__.py
pyvisual-0.65.dist-info/LICENSE.txt
pyvisual-0.65.dist-info/METADATA
pyvisual-0.65.dist-info/WHEEL
pyvisual-0.65.dist-info/top_level.txt
pyvisual-0.65.dist-info/RECORD
