Metadata-Version: 2.1
Name: pyvisual
Version: 0.65
Summary: A Python GUI Creator for Humans
Home-page: https://github.com/user/reponame
Download-URL: https://github.com/user/reponame/archive/v_01.tar.gz
Author: Murtaza Hassan
Author-email: contact@murtazahassan.com
License: MIT
Keywords: GUI,UI,Graphical Interface,User Interface
Classifier: Development Status :: 3 - Alpha
Classifier: Intended Audience :: Developers
Classifier: Topic :: Software Development :: Build Tools
Classifier: License :: OSI Approved :: MIT License
Classifier: Programming Language :: Python :: 3
Requires-Python: >=3.7
License-File: LICENSE.txt
Requires-Dist: PySide6
Requires-Dist: pyqtgraph
